.gitignore
LICENSE
README.md
deploy.sh
pyproject.toml
requirements.txt
setup.py
.github/workflows/publish.yml
.idea/.gitignore
.idea/misc.xml
.idea/mkdocs-minecraft.iml
.idea/modules.xml
.idea/vcs.xml
.idea/inspectionProfiles/profiles_settings.xml
mkdocs_minecraft/__init__.py
mkdocs_minecraft/config.py
mkdocs_minecraft/plugin.py
mkdocs_minecraft/render.py
mkdocs_minecraft.egg-info/PKG-INFO
mkdocs_minecraft.egg-info/SOURCES.txt
mkdocs_minecraft.egg-info/dependency_links.txt
mkdocs_minecraft.egg-info/entry_points.txt
mkdocs_minecraft.egg-info/requires.txt
mkdocs_minecraft.egg-info/top_level.txt
mkdocs_minecraft/font/Minecraft.ttf
mkdocs_minecraft/textures/background.png
mkdocs_minecraft/textures/background_smelting.png
mkdocs_minecraft/textures/minecraft/acacia_boat.png
mkdocs_minecraft/textures/minecraft/acacia_button_inventory.png
mkdocs_minecraft/textures/minecraft/acacia_chest_boat.png
mkdocs_minecraft/textures/minecraft/acacia_door.png
mkdocs_minecraft/textures/minecraft/acacia_door_bottom.png
mkdocs_minecraft/textures/minecraft/acacia_door_top.png
mkdocs_minecraft/textures/minecraft/acacia_fence_gate.png
mkdocs_minecraft/textures/minecraft/acacia_fence_inventory.png
mkdocs_minecraft/textures/minecraft/acacia_hanging_sign.png
mkdocs_minecraft/textures/minecraft/acacia_leaves.png
mkdocs_minecraft/textures/minecraft/acacia_log.png
mkdocs_minecraft/textures/minecraft/acacia_log_horizontal.png
mkdocs_minecraft/textures/minecraft/acacia_log_top.png
mkdocs_minecraft/textures/minecraft/acacia_planks.png
mkdocs_minecraft/textures/minecraft/acacia_pressure_plate.png
mkdocs_minecraft/textures/minecraft/acacia_sapling.png
mkdocs_minecraft/textures/minecraft/acacia_sign.png
mkdocs_minecraft/textures/minecraft/acacia_slab.png
mkdocs_minecraft/textures/minecraft/acacia_stairs.png
mkdocs_minecraft/textures/minecraft/acacia_trapdoor-edge.png
mkdocs_minecraft/textures/minecraft/acacia_trapdoor.png
mkdocs_minecraft/textures/minecraft/acacia_trapdoor_bottom.png
mkdocs_minecraft/textures/minecraft/acacia_wood.png
mkdocs_minecraft/textures/minecraft/activator_rail.png
mkdocs_minecraft/textures/minecraft/activator_rail_on.png
mkdocs_minecraft/textures/minecraft/allium.png
