Metadata-Version: 2.1
Name: mkdocs-minecraft
Version: 0.3.0
Summary: A MkDocs Minecraft Recipes plugin
Home-page: 
Author: Katzen48 | Tobi
Author-email: Katzen48 | Tobi <admin@katzen48.de>
License: MIT
Keywords: mkdocs
Classifier: Development Status :: 4 - Beta
Classifier: Intended Audience :: Developers
Classifier: Intended Audience :: Information Technology
Classifier: License :: OSI Approved :: MIT License
Classifier: Programming Language :: Python
Requires-Python: >=3.7
License-File: LICENSE
Requires-Dist: mkdocs>=1.5.3
